bankvpn/__init__.py
bankvpn/__version__.py
bankvpn/bke_vpn.py
bankvpn/common.py
bankvpn/main.py
bankvpn-1.1.3.dist-info/LICENSE
bankvpn-1.1.3.dist-info/METADATA
bankvpn-1.1.3.dist-info/WHEEL
bankvpn-1.1.3.dist-info/entry_points.txt
bankvpn-1.1.3.dist-info/top_level.txt
bankvpn-1.1.3.dist-info/RECORD
