Metadata-Version: 2.1
Name: bankvpn
Version: 1.1.3
Summary: A Tool to connect vpn
Home-page: 
Author: jiagui.lin
Author-email: jiagui.lin@shopee.com
Classifier: Programming Language :: Python :: 3
Classifier: License :: OSI Approved :: MIT License
Classifier: Operating System :: OS Independent
License-File: LICENSE
Requires-Dist: certifi ==2023.5.7
Requires-Dist: charset-normalizer ==3.1.0
Requires-Dist: click ==8.1.3
Requires-Dist: idna ==3.4
Requires-Dist: importlib-metadata ==6.6.0
Requires-Dist: jaraco.classes ==3.2.3
Requires-Dist: Jinja2 ==3.1.2
Requires-Dist: keyring ==23.13.1
Requires-Dist: MarkupSafe ==2.1.2
Requires-Dist: more-itertools ==9.1.0
Requires-Dist: pexpect ==4.8.0
Requires-Dist: ptyprocess ==0.7.0
Requires-Dist: PyYAML ==6.0
Requires-Dist: requests ==2.31.0
Requires-Dist: urllib3 ==2.0.2
Requires-Dist: zipp ==3.15.0
